{
    "format_version": "1.12",
    "minecraft:recipe_shaped": {
      "description": {
      "identifier": "minecraft:record_11"
      },
  
      
      "tags": [ "crafting_table" ],
      "pattern": [
        "AXB",
        "X#X",
        "BXA"
      ],
      "key": {
        "#": {
          "item": "minecraft:diamond"
        },
        "X": {
          "item": "minecraft:iron_ingot"
        },
        "A":{
            "item": "minecraft:wheat"
        },
        "B":{
            "item": "minecraft:wool"
        }
      },
      "result": {
        "item": "minecraft:record_11"
      }
    }
  }